ipynb_convert/__init__.py
ipynb_convert/convert.py
ipynb_convert-1.0.1.dist-info/LICENSE
ipynb_convert-1.0.1.dist-info/METADATA
ipynb_convert-1.0.1.dist-info/WHEEL
ipynb_convert-1.0.1.dist-info/top_level.txt
ipynb_convert-1.0.1.dist-info/RECORD
