Metadata-Version: 2.1
Name: ipynb_convert
Version: 1.0.1
Summary: A package that can convert a Jupyter Notebook into a single Python file
Author-email: Vedant Singhania <vedant.singhania@gmail.com.com>
Project-URL: Homepage, https://github.com/raspberri05/ipynb_convert
Project-URL: Issues, https://github.com/raspberri05/ipynb_convert/issues
Classifier: Programming Language :: Python :: 3
Classifier: License :: OSI Approved :: MIT License
Classifier: Operating System :: OS Independent
Requires-Python: >=3.8
License-File: LICENSE
